LICENSE
MANIFEST.in
README.md
setup.py
asyncio_helpers/__init__.py
asyncio_helpers/__version__.py
asyncio_helpers/decorators.py
asyncio_helpers.egg-info/PKG-INFO
asyncio_helpers.egg-info/SOURCES.txt
asyncio_helpers.egg-info/dependency_links.txt
asyncio_helpers.egg-info/requires.txt
asyncio_helpers.egg-info/top_level.txt