Metadata-Version: 2.1
Name: asyncio-helpers
Version: 0.0.2
Summary: Nifty helpers to work with asyncio
Home-page: https://github.com/niranjan94/asyncio-helpers
Author: Niranjan Rajendran
Author-email: me@niranjan.io
License: MIT
Platform: UNKNOWN
Classifier: License :: OSI Approved :: MIT License
Classifier: Programming Language :: Python
Classifier: Programming Language :: Python :: 3
Classifier: Programming Language :: Python :: 3.6
Classifier: Programming Language :: Python :: 3.7
Classifier: Programming Language :: Python :: Implementation :: CPython
Classifier: Programming Language :: Python :: Implementation :: PyPy
Requires-Python: >=3.6.0
